graphalgorithmplayer/GraphAlgorithmPlayer.py
graphalgorithmplayer/GraphAlgorithmView.py
graphalgorithmplayer/GraphViewBQPlot.py
graphalgorithmplayer/GraphViewNetworkx.py
graphalgorithmplayer/GraphViewNx.py
graphalgorithmplayer/VariablesView.py
graphalgorithmplayer/__init__.py
graphalgorithmplayer/graph.py
graphalgorithmplayer/graph_examples.py
graphalgorithmplayer/graph_networkx.py
graphalgorithmplayer-0.1.0.dist-info/LICENSE.txt
graphalgorithmplayer-0.1.0.dist-info/METADATA
graphalgorithmplayer-0.1.0.dist-info/WHEEL
graphalgorithmplayer-0.1.0.dist-info/top_level.txt
graphalgorithmplayer-0.1.0.dist-info/RECORD
