Metadata-Version: 2.1
Name: graphalgorithmplayer
Version: 0.1.0
Summary: A Player to display graph processing
Home-page: https://gitlab.u-psud.fr/edwige.gros/GraphAlgorithmPlayer/tree/master/GraphAlgorithmPlayer
Author: Edwige Gros
Author-email: edwige.gros@laposte.net
License: UNKNOWN
Platform: UNKNOWN
Classifier: Programming Language :: Python :: 3
Classifier: License :: OSI Approved :: MIT License
Classifier: Operating System :: OS Independent
Requires-Python: >=3.6
Requires-Dist: timer
Requires-Dist: ipywidgets
Requires-Dist: valueplayerwidget
Requires-Dist: networkx
Requires-Dist: traitlets
Requires-Dist: bqplot
Requires-Dist: matplotlib
